rock_paper_scissors/__init__.py
rock_paper_scissors/envs/__init__.py
rock_paper_scissors/envs/rps_env.py
rock_paper_scissors-0.0.2.dist-info/LICENSE
rock_paper_scissors-0.0.2.dist-info/METADATA
rock_paper_scissors-0.0.2.dist-info/WHEEL
rock_paper_scissors-0.0.2.dist-info/top_level.txt
rock_paper_scissors-0.0.2.dist-info/RECORD
