Metadata-Version: 2.1
Name: rock-paper-scissors
Version: 0.0.2
Summary: A RL environment for rock paper scissors(deterministic)  based on openai
Home-page: https://github.com/raul1991/rock-paper-scissors-RL
Author: Rahul Bawa
Author-email: hi.rahulbawa@gmail.com
License: UNKNOWN
Platform: UNKNOWN
Classifier: Programming Language :: Python :: 3
Classifier: License :: OSI Approved :: MIT License
Classifier: Operating System :: OS Independent
Requires-Dist: gym
Requires-Dist: numpy
